dpgui/__init__.py
dpgui/cli.py
dpgui/dargs.py
dpgui/web.py
dpgui/dist/index.html
dpgui/dist/manifest.json
dpgui/dist/robots.txt
dpgui/dist/service-worker.js
dpgui/dist/service-worker.js.map
dpgui/dist/workbox-db5fc017.js
dpgui/dist/workbox-db5fc017.js.map
dpgui/dist/css/chunk-vendors.bdfb7e85.css
dpgui/dist/css/input.28e33fe0.css
dpgui/dist/fonts/fa-brands-400.8bf6ccf0.ttf
dpgui/dist/fonts/fa-brands-400.e465758e.woff2
dpgui/dist/fonts/fa-regular-400.a937b755.ttf
dpgui/dist/fonts/fa-regular-400.f386b6b7.woff2
dpgui/dist/fonts/fa-solid-900.081655f2.ttf
dpgui/dist/fonts/fa-solid-900.ce4938a3.woff2
dpgui/dist/fonts/fa-v4compatibility.f8c4829c.ttf
dpgui/dist/js/app.e18ae01c.js
dpgui/dist/js/app.e18ae01c.js.map
dpgui/dist/js/args10.8fbd4b69.js
dpgui/dist/js/args11.08a84d05.js
dpgui/dist/js/args14.2c822766.js
dpgui/dist/js/args15.9f8cb9a9.js
dpgui/dist/js/args18.8ea8b064.js
dpgui/dist/js/args19.41c1078f.js
dpgui/dist/js/args2.96728bec.js
dpgui/dist/js/args22.488d8a9b.js
dpgui/dist/js/args24.7acdf691.js
dpgui/dist/js/args26.bfb2739f.js
dpgui/dist/js/args27.9e38a25f.js
dpgui/dist/js/args30.fc27e7bc.js
dpgui/dist/js/args4.be70634c.js
dpgui/dist/js/args6.36d86a54.js
dpgui/dist/js/args8.3d0ba019.js
dpgui/dist/js/chunk-vendors.a2a541cb.js
dpgui/dist/js/chunk-vendors.a2a541cb.js.map
dpgui/dist/js/input.8d300c99.js
dpgui/dist/js/input.8d300c99.js.map
dpgui-1.0.1.dist-info/METADATA
dpgui-1.0.1.dist-info/WHEEL
dpgui-1.0.1.dist-info/entry_points.txt
dpgui-1.0.1.dist-info/licenses/LICENSE
dpgui-1.0.1.dist-info/RECORD
