Metadata-Version: 2.3
Name: dpgui
Version: 1.0.1
Summary: A web-based GUI for user inputs.
Project-URL: repository, https://github.com/deepmodeling/dpgui
Author: DeepModeling
License:                    GNU LESSER GENERAL PUBLIC LICENSE
Keywords: gui
Classifier: License :: OSI Approved :: GNU Lesser General Public License v3 (LGPLv3)
Classifier: Operating System :: MacOS :: MacOS X
Classifier: Operating System :: Microsoft :: Windows
Classifier: Operating System :: POSIX :: Linux
Classifier: Programming Language :: Python :: 3.7
Classifier: Programming Language :: Python :: 3.8
Classifier: Programming Language :: Python :: 3.9
Classifier: Programming Language :: Python :: 3.10
Classifier: Programming Language :: Python :: 3.11
Requires-Python: >=3.7
Requires-Dist: dargs>=0.2.6
Requires-Dist: importlib-metadata>=1.4; python_version < '3.8'
Requires-Dist: waitress
Requires-Dist: werkzeug
